easy_pastebin/__init__.py
easy_pastebin/mainlib.py
easy_pastebin-1.0.dist-info/LICENSE
easy_pastebin-1.0.dist-info/METADATA
easy_pastebin-1.0.dist-info/WHEEL
easy_pastebin-1.0.dist-info/top_level.txt
easy_pastebin-1.0.dist-info/RECORD
