Metadata-Version: 2.1
Name: easy_pastebin
Version: 1.0
License: MIT
License-File: LICENSE
Requires-Dist: requests
